database_factory/.version
database_factory/__init__.py
database_factory/manager.py
database_factory/operations.py
database_factory/cloud/__init__.py
database_factory/cloud/aws/__init__.py
database_factory/cloud/aws/auth.py
database_factory/cloud/aws/secrete_manager.py
database_factory/cloud/gcp/__init__.py
database_factory/cloud/gcp/auth.py
database_factory/cloud/gcp/resource_manager.py
database_factory/cloud/gcp/secrete_manager.py
database_factory/common/__init__.py
database_factory/common/common.py
database_factory-1.1.1.dist-info/LICENSE
database_factory-1.1.1.dist-info/METADATA
database_factory-1.1.1.dist-info/WHEEL
database_factory-1.1.1.dist-info/top_level.txt
database_factory-1.1.1.dist-info/RECORD
